tiers/__init__.py
tiers/admin.py
tiers/app_settings.py
tiers/apps.py
tiers/helpers.py
tiers/instrumentation.py
tiers/middleware.py
tiers/models.py
tiers/tier_info.py
tiers/waffle_utils.py
tiers/migrations/0001_initial.py
tiers/migrations/0002_auto_20170321_1856.py
tiers/migrations/0003_auto_20170321_1941.py
tiers/migrations/0004_auto_20170321_2011.py
tiers/migrations/0005_auto_20200907_1111.py
tiers/migrations/__init__.py
tiers/tests/__init__.py
tiers/tests/factories.py
tiers/tests/test_admin.py
tiers/tests/test_tiers.py
django_tiers-0.2.8.dist-info/AUTHORS
django_tiers-0.2.8.dist-info/LICENSE
django_tiers-0.2.8.dist-info/METADATA
django_tiers-0.2.8.dist-info/WHEEL
django_tiers-0.2.8.dist-info/top_level.txt
django_tiers-0.2.8.dist-info/RECORD
