Metadata-Version: 2.1
Name: django-tiers
Version: 0.2.8
Summary: Django tier management
Home-page: https://github.com/appsembler/django-tiers
Author: Appsembler
License: MIT
Classifier: Development Status :: 3 - Alpha
Classifier: Environment :: Web Environment
Classifier: Intended Audience :: Developers
Classifier: Operating System :: OS Independent
Classifier: Programming Language :: Python
Classifier: Framework :: Django
License-File: LICENSE
License-File: AUTHORS
Requires-Dist: django (<4)
Requires-Dist: django-model-utils
Requires-Dist: python-dateutil
